{"stats":[{"globalRank":"320,301","turkeyRank":"6,897","globalRankOld":"319,682","turkeyRankOld":"6,794","site":"duzcetv.com","url":"http://www.duzcetv.com/","city":"81"},{"globalRank":"752,651","turkeyRank":"10,787","globalRankOld":"793,697","turkeyRankOld":"11,768","site":"oxijen.tv","url":"http://www.oxijen.tv/","city":"81"},{"globalRank":"644,731","turkeyRank":"18,998","globalRankOld":"662,197","turkeyRankOld":"21,216","site":"duzcepostasi.com","url":"http://www.duzcepostasi.com/","city":"81"},{"globalRank":"198,671","turkeyRank":"3,421","globalRankOld":"202,845","turkeyRankOld":"3,538","site":"duzceninsesi.com.tr","url":"http://www.duzceninsesi.com.tr/","city":"81"},{"globalRank":"203,425","turkeyRank":"4,192","globalRankOld":"204,677","turkeyRankOld":"4,280","site":"duzceparantez.com","url":"http://www.duzceparantez.com/","city":"81"},{"globalRank":"299,825","turkeyRank":"3,547","globalRankOld":"304,896","turkeyRankOld":"3,530","site":"gunaydinduzce.com","url":"http://www.gunaydinduzce.com/","city":"81"},{"globalRank":"6,150,789","turkeyRank":null,"globalRankOld":"6,150,789","turkeyRankOld":null,"site":"maviduzce.com","url":"http://www.maviduzce.com/","city":"81"},{"globalRank":"108,928","turkeyRank":"1,620","globalRankOld":"109,289","turkeyRankOld":"1,642","site":"burasiduzce.com","url":"http://www.burasiduzce.com/","city":"81"},{"globalRank":"480,408","turkeyRank":"14,625","globalRankOld":"488,287","turkeyRankOld":"16,476","site":"duzcerota.com","url":"http://www.duzcerota.com/","city":"81"},{"globalRank":"383,209","turkeyRank":"6,641","globalRankOld":"388,428","turkeyRankOld":"6,791","site":"duzcesonhaber.com","url":"http://www.duzcesonhaber.com/","city":"81"},{"globalRank":"360,348","turkeyRank":"9,193","globalRankOld":"361,113","turkeyRankOld":"9,432","site":"duzceyerelhaber.com","url":"http://duzceyerelhaber.com/","city":"81"},{"globalRank":"169,787","turkeyRank":"3,078","globalRankOld":"170,502","turkeyRankOld":"3,179","site":"akcakocatv.com","url":"http://akcakocatv.com/","city":"81"},{"globalRank":"1,235,349","turkeyRank":"52,331","globalRankOld":"1,260,072","turkeyRankOld":"58,443","site":"duzcedetay.com","url":"http://duzcedetay.com/","city":"81"},{"globalRank":"1,630,342","turkeyRank":null,"globalRankOld":"1,630,605","turkeyRankOld":"104,498","site":"duzceobjektif.com","url":"http://duzceobjektif.com/","city":"81"},{"globalRank":"1,613,482","turkeyRank":"29,837","globalRankOld":"1,613,768","turkeyRankOld":"27,933","site":"bizbolulular.com","url":"http://www.bizbolulular.com/","city":"14"},{"globalRank":"1,854,872","turkeyRank":"79,837","globalRankOld":"1,855,833","turkeyRankOld":"79,954","site":"duzcemanset.com.tr","url":"http://www.duzcemanset.com.tr/","city":"81"},{"globalRank":"114,900","turkeyRank":"1,871","globalRankOld":"115,706","turkeyRankOld":"1,880","site":"oncurtv.com","url":"http://www.oncurtv.com/","city":"81"},{"globalRank":"2,498,364","turkeyRank":null,"globalRankOld":"2,499,802","turkeyRankOld":"78,609","site":"81oraytv.com","url":"http://www.81oraytv.com/","city":"81"},{"globalRank":"765,503","turkeyRank":"24,897","globalRankOld":"799,644","turkeyRankOld":"28,459","site":"duzcedamla.com","url":"http://www.duzcedamla.com/","city":"81"},{"globalRank":"8,057,504","turkeyRank":null,"globalRankOld":"8,057,504","turkeyRankOld":null,"site":"duzcearti.com","url":"http://www.duzcearti.com/","city":"81"},{"globalRank":"2,314,428","turkeyRank":null,"globalRankOld":"2,315,918","turkeyRankOld":"82,535","site":"duzcetakip.com","url":"http://duzcetakip.com/","city":"81"},{"globalRank":"6,027,908","turkeyRank":null,"globalRankOld":"6,027,908","turkeyRankOld":null,"site":"haberozel.com.tr","url":"https://haberozel.com.tr/","city":"81"},{"globalRank":"1,814,998","turkeyRank":"66,962","globalRankOld":"1,815,853","turkeyRankOld":"66,997","site":"duzcelife.com","url":"http://www.duzcelife.com/","city":"81"},{"globalRank":"5,887,879","turkeyRank":null,"globalRankOld":"5,887,879","turkeyRankOld":null,"site":"duzcehavadis.net","url":"http://www.duzcehavadis.net/","city":"81"},{"globalRank":"1,066,714","turkeyRank":"27,444","globalRankOld":"1,089,482","turkeyRankOld":"27,123","site":"duzcepusula.com","url":"http://www.duzcepusula.com/","city":"81"},{"globalRank":"8,437,929","turkeyRank":null,"globalRankOld":"8,437,929","turkeyRankOld":null,"site":"memleketimduzce.com","url":"http://www.memleketimduzce.com/","city":"81"},{"globalRank":"1,540,670","turkeyRank":"38,055","globalRankOld":"1,541,139","turkeyRankOld":"38,160","site":"malumathaber.com","url":"http://www.malumathaber.com/","city":"81"},{"globalRank":"2,115,144","turkeyRank":"59,018","globalRankOld":"2,116,241","turkeyRankOld":"59,084","site":"habergercek.org","url":"http://www.habergercek.org/","city":"81"},{"globalRank":"343,155","turkeyRank":"10,093","globalRankOld":"343,225","turkeyRankOld":"9,775","site":"haberolduk.com","url":"http://www.haberolduk.com/","city":"81"},{"globalRank":"7,306,659","turkeyRank":null,"globalRankOld":"7,306,659","turkeyRankOld":null,"site":"duzcehurhaber.com","url":"http://www.duzcehurhaber.com/","city":"81"},{"globalRank":"4,548,690","turkeyRank":null,"globalRankOld":"4,548,690","turkeyRankOld":null,"site":"duzcedebugun.com","url":"http://www.duzcedebugun.com/","city":"81"},{"globalRank":"2,468,772","turkeyRank":null,"globalRankOld":"2,470,116","turkeyRankOld":"100,240","site":"merkeztv.com.tr","url":"http://www.merkeztv.com.tr/","city":"14"},{"globalRank":"6,450,270","turkeyRank":null,"globalRankOld":"6,450,270","turkeyRankOld":null,"site":"duzceanaliz.com","url":"http://www.duzceanaliz.com/","city":"81"},{"globalRank":"5,893,807","turkeyRank":null,"globalRankOld":"5,893,807","turkeyRankOld":null,"site":"duzcekent.com","url":"http://duzcekent.com/","city":"81"},{"globalRank":"1,860,857","turkeyRank":"75,879","globalRankOld":"1,861,832","turkeyRankOld":"68,331","site":"haber380.com","url":"http://haber380.com/","city":"81"},{"globalRank":"259,315","turkeyRank":"8,985","globalRankOld":"259,184","turkeyRankOld":"9,137","site":"medyajans.com","url":"https://www.medyajans.com/","city":"0"},{"globalRank":"5,340","turkeyRank":"132","globalRankOld":"5,390","turkeyRankOld":"133","site":"superhaber.tv","url":"http://superhaber.tv/","city":"0"},{"globalRank":"2,197","turkeyRank":"41","globalRankOld":"2,196","turkeyRankOld":"42","site":"haber7.com","url":"http://www.haber7.com/","city":"0"},{"globalRank":"1,232","turkeyRank":"36","globalRankOld":"1,231","turkeyRankOld":"34","site":"trthaber.com","url":"http://www.trthaber.com/","city":"0"},{"globalRank":"1,876","turkeyRank":"46","globalRankOld":"1,872","turkeyRankOld":"47","site":"ntv.com.tr","url":"https://www.ntv.com.tr/","city":"0"},{"globalRank":"1,428","turkeyRank":"67","globalRankOld":"1,411","turkeyRankOld":"63","site":"aa.com.tr","url":"http://www.aa.com.tr/","city":"0"},{"globalRank":"3,028","turkeyRank":"83","globalRankOld":"3,055","turkeyRankOld":"82","site":"cnnturk.com","url":"http://www.cnnturk.com/","city":"0"},{"globalRank":"428","turkeyRank":"9","globalRankOld":"430","turkeyRankOld":"9","site":"ensonhaber.com","url":"http://ensonhaber.com/","city":"0"},{"globalRank":"1,175","turkeyRank":"22","globalRankOld":"1,178","turkeyRankOld":"22","site":"haberturk.com","url":"https://www.haberturk.com/","city":"0"},{"globalRank":"18,827","turkeyRank":"172","globalRankOld":"20,255","turkeyRankOld":"192","site":"iha.com.tr","url":"http://www.iha.com.tr/","city":"0"},{"globalRank":"1,412","turkeyRank":"26","globalRankOld":"1,434","turkeyRankOld":"27","site":"haberler.com","url":"http://www.haberler.com/","city":"0"},{"globalRank":"15,923","turkeyRank":"318","globalRankOld":"15,981","turkeyRankOld":"319","site":"ahaber.com.tr","url":"http://www.ahaber.com.tr/","city":"0"},{"globalRank":"6,941","turkeyRank":"174","globalRankOld":"6,989","turkeyRankOld":"173","site":"internethaber.com","url":"http://www.internethaber.com/","city":"0"},{"globalRank":"10,594","turkeyRank":"202","globalRankOld":"10,576","turkeyRankOld":"201","site":"dha.com.tr","url":"http://www.dha.com.tr/","city":"0"},{"globalRank":"40,212","turkeyRank":"729","globalRankOld":"39,891","turkeyRankOld":"739","site":"veryansintv.com","url":"https://veryansintv.com/","city":"0"},{"globalRank":"104","turkeyRank":"111","globalRankOld":"103","turkeyRankOld":"113","site":"bbc.com","url":"https://www.bbc.com/turkce","city":"0"},{"globalRank":"24,117","turkeyRank":"432","globalRankOld":"23,994","turkeyRankOld":"431","site":"diken.com.tr","url":"http://www.diken.com.tr/","city":"0"},{"globalRank":"871","turkeyRank":"129","globalRankOld":"867","turkeyRankOld":"127","site":"tr.sputniknews.com","url":"https://tr.sputniknews.com/","city":"0"},{"globalRank":"4,697","turkeyRank":"105","globalRankOld":"4,668","turkeyRankOld":"104","site":"t24.com.tr","url":"http://www.t24.com.tr/","city":"0"},{"globalRank":"59,977","turkeyRank":"1,279","globalRankOld":"59,708","turkeyRankOld":"1,263","site":"amerikaninsesi.com","url":"https://www.amerikaninsesi.com/","city":"0"},{"globalRank":"12,564","turkeyRank":"196","globalRankOld":"12,607","turkeyRankOld":"199","site":"gercekgundem.com","url":"http://www.gercekgundem.com/","city":"0"},{"globalRank":"2,136","turkeyRank":"269","globalRankOld":"2,125","turkeyRankOld":"273","site":"tr.euronews.com","url":"https://tr.euronews.com/","city":"0"},{"globalRank":"42,949","turkeyRank":"663","globalRankOld":"42,919","turkeyRankOld":"664","site":"f5haber.com","url":"http://www.f5haber.com/","city":"0"},{"globalRank":"657","turkeyRank":"172","globalRankOld":"654","turkeyRankOld":"170","site":"dw.com","url":"https://www.dw.com/","city":"0"},{"globalRank":"27,723","turkeyRank":"549","globalRankOld":"27,501","turkeyRankOld":"547","site":"beyazgazete.com","url":"http://www.beyazgazete.com/","city":"0"},{"globalRank":"20,956","turkeyRank":"406","globalRankOld":"20,998","turkeyRankOld":"407","site":"indyturk.com","url":"https://indyturk.com/","city":"0"},{"globalRank":"6,764","turkeyRank":"154","globalRankOld":"6,763","turkeyRankOld":"150","site":"memurlar.net","url":"http://www.memurlar.net/","city":"0"},{"globalRank":"6,161","turkeyRank":"179","globalRankOld":"6,129","turkeyRankOld":"175","site":"gazetevatan.com","url":"http://www.gazetevatan.com/","city":"0"},{"globalRank":"20,412","turkeyRank":"386","globalRankOld":"20,341","turkeyRankOld":"381","site":"haber3.com","url":"http://www.haber3.com/","city":"0"},{"globalRank":"476,268","turkeyRank":"16,095","globalRankOld":"473,642","turkeyRankOld":"16,134","site":"stargazete.com","url":"http://www.stargazete.com/","city":"0"},{"globalRank":"3,872","turkeyRank":"93","globalRankOld":"3,873","turkeyRankOld":"94","site":"sondakika.com","url":"https://www.sondakika.com/","city":"0"},{"globalRank":"41,992","turkeyRank":"647","globalRankOld":"41,849","turkeyRankOld":"648","site":"medyafaresi.com","url":"http://www.medyafaresi.com/","city":"0"},{"globalRank":"125,880","turkeyRank":"2,489","globalRankOld":"127,055","turkeyRankOld":"2,470","site":"medyascope.tv","url":"https://medyascope.tv/","city":"0"},{"globalRank":"839","turkeyRank":"19","globalRankOld":"840","turkeyRankOld":"20","site":"mynet.com","url":"https://www.mynet.com/","city":"0"},{"globalRank":"28,665","turkeyRank":"472","globalRankOld":"28,614","turkeyRankOld":"470","site":"turktime.com","url":"http://www.turktime.com/","city":"0"},{"globalRank":"941,892","turkeyRank":"39,593","globalRankOld":"916,171","turkeyRankOld":"39,740","site":"hurhaber.com","url":"http://www.hurhaber.com/","city":"0"},{"globalRank":"556,008","turkeyRank":"17,320","globalRankOld":"556,789","turkeyRankOld":"16,788","site":"objektifhaber.com","url":"http://www.objektifhaber.com/","city":"0"},{"globalRank":"93,051","turkeyRank":"1,926","globalRankOld":"92,291","turkeyRankOld":"1,873","site":"habervakti.com","url":"http://www.habervakti.com/","city":"0"},{"globalRank":"975,575","turkeyRank":"41,806","globalRankOld":"991,799","turkeyRankOld":"45,298","site":"eurovizyon.co.uk","url":"http://www.eurovizyon.co.uk/","city":"0"},{"globalRank":"389,317","turkeyRank":"10,719","globalRankOld":"387,278","turkeyRankOld":"11,204","site":"habervitrini.com","url":"http://www.habervitrini.com/","city":"0"},{"globalRank":"1,566,452","turkeyRank":"47,833","globalRankOld":"1,535,222","turkeyRankOld":"45,187","site":"bigpara.com","url":"http://www.bigpara.com/","city":"0"},{"globalRank":"103,303","turkeyRank":"1,785","globalRankOld":"103,421","turkeyRankOld":"1,788","site":"tgrthaber.com.tr","url":"http://www.tgrthaber.com.tr/","city":"0"},{"globalRank":"325,050","turkeyRank":"7,635","globalRankOld":"324,632","turkeyRankOld":"7,395","site":"pressturk.com","url":"http://www.pressturk.com/","city":"0"},{"globalRank":"40,952","turkeyRank":"697","globalRankOld":"40,906","turkeyRankOld":"699","site":"timeturk.com","url":"http://www.timeturk.com/","city":"0"},{"globalRank":"633,624","turkeyRank":"19,468","globalRankOld":"634,734","turkeyRankOld":"19,044","site":"netgazete.com","url":"http://www.netgazete.com/","city":"0"}],"lastUpdated":"July 4, 2021, 15:18"}